pyshad/__init__.py
pyshad/client.py
pyshad/exceptions.py
pyshad/filters.py
pyshad/handlers.py
pyshad/network.py
pyshad/sync.py
pyshad/utils.py
pyshad/bots/__init__.py
pyshad/bots/client.py
pyshad/crypto/__init__.py
pyshad/crypto/crypto.py
pyshad/enums/__init__.py
pyshad/enums/chat_access_type.py
pyshad/enums/chat_action.py
pyshad/enums/chat_type.py
pyshad/enums/message_media_type.py
pyshad/enums/poll_type.py
pyshad/enums/reaction_type.py
pyshad/methods/__init__.py
pyshad/methods/advanced/__init__.py
pyshad/methods/advanced/build.py
pyshad/methods/auth/__init__.py
pyshad/methods/auth/register_device.py
pyshad/methods/auth/send_code.py
pyshad/methods/auth/sign_in.py
pyshad/methods/channels/__init__.py
pyshad/methods/channels/add_channel.py
pyshad/methods/channels/add_channel_members.py
pyshad/methods/channels/ban_channel_member.py
pyshad/methods/channels/channel_preview_by_join_link.py
pyshad/methods/channels/check_channel_username.py
pyshad/methods/channels/create_channel_voice_chat.py
pyshad/methods/channels/delete_no_access_group_chat.py
pyshad/methods/channels/discard_channel_voice_chat.py
pyshad/methods/channels/edit_channel_info.py
pyshad/methods/channels/get_banned_group_members.py
pyshad/methods/channels/get_channel_admin_access_list.py
pyshad/methods/channels/get_channel_admin_members.py
pyshad/methods/channels/get_channel_all_members.py
pyshad/methods/channels/get_channel_info.py
pyshad/methods/channels/get_channel_link.py
pyshad/methods/channels/get_group_default_access.py
pyshad/methods/channels/get_group_mention_list.py
pyshad/methods/channels/get_group_voice_chat_updates.py
pyshad/methods/channels/join_channel_action.py
pyshad/methods/channels/join_channel_by_link.py
pyshad/methods/channels/join_group.py
pyshad/methods/channels/leave_group.py
pyshad/methods/channels/leave_group_voice_chat.py
pyshad/methods/channels/remove_channel.py
pyshad/methods/channels/seen_channel_messages.py
pyshad/methods/channels/set_channel_link.py
pyshad-0.0.1.dist-info/METADATA
pyshad-0.0.1.dist-info/WHEEL
pyshad-0.0.1.dist-info/top_level.txt
pyshad-0.0.1.dist-info/RECORD
