Metadata-Version: 2.1
Name: pyshad
Version: 0.0.1
Summary: It`s an unofficial library for deploying robots on Shad accounts.
Home-page: https://github.com/LinuxV3/pyshad
Author: LinuxV3
Author-email: contact@LinuxV3.info
Keywords: pyshad,pyrubi,shad,shadpy,robot,rubpy
Classifier: Programming Language :: Python :: 3.7
Classifier: Programming Language :: Python :: 3.8
Classifier: Programming Language :: Python :: 3.9
Classifier: Programming Language :: Python :: 3.10
Classifier: Programming Language :: Python :: 3.11
Classifier: Programming Language :: Python :: 3.12
Classifier: License :: OSI Approved :: GNU Lesser General Public License v3 (LGPLv3)
Classifier: Topic :: Internet
Classifier: Topic :: Communications
Classifier: Topic :: Communications :: Chat
Classifier: Topic :: Software Development :: Libraries
Classifier: Topic :: Software Development :: Libraries :: Python Modules
Classifier: Topic :: Software Development :: Libraries :: Application Frameworks
Requires-Python: ~=3.7
Requires-Dist: aiohttp
Requires-Dist: pycryptodome
Requires-Dist: pydantic ==1.10.12
Requires-Dist: aiofiles
Provides-Extra: cv
Requires-Dist: opencv-python ; extra == 'cv'
Provides-Extra: pil
Requires-Dist: pillow ; extra == 'pil'
